htmlrag/__init__.py
htmlrag/html_utils.py
htmlrag/pruner.py
htmlrag-0.1.1.dist-info/LICENSE
htmlrag-0.1.1.dist-info/METADATA
htmlrag-0.1.1.dist-info/WHEEL
htmlrag-0.1.1.dist-info/top_level.txt
htmlrag-0.1.1.dist-info/RECORD
