Metadata-Version: 2.2
Name: htmlrag
Version: 0.1.1
Summary: A smart toolkit for HTML cleaning and pruning for RAG systems.
Author: zstanjj
Author-email: zstanjj <zstanjj@gmail.com>
Maintainer-email: zstanjj <zstanjj@gmail.com>
License: MIT License
Project-URL: Homepage, https://github.com/plageon/HtmlRAG
Project-URL: Issues, https://github.com/plageon/HtmlRAG/issues
Keywords: html,rag,transformers,nlp,cleaning,pruning
Platform: UNKNOWN
Classifier: Programming Language :: Python :: 3
Classifier: License :: OSI Approved :: MIT License
Classifier: Operating System :: OS Independent
Requires-Python: >=3.8
License-File: LICENSE
Requires-Dist: lxml
Requires-Dist: httpx-sse
Requires-Dist: torch
Requires-Dist: pydantic-settings
Requires-Dist: bs4
Requires-Dist: transformers
Requires-Dist: sentence-transformers
Requires-Dist: torch
Requires-Dist: numpy
Requires-Dist: langchain
Requires-Dist: langchain-core>=0.3.0
Requires-Dist: langchain-huggingface
Requires-Dist: anytree
Requires-Dist: langchain-community>=0.3.0
Requires-Dist: faiss-cpu
